ginodantic/__init__.py
ginodantic/gino_model_meta.py
ginodantic/schemas.py
ginodantic/utils.py
ginodantic-0.1.0b2.dist-info/LICENSE.txt
ginodantic-0.1.0b2.dist-info/METADATA
ginodantic-0.1.0b2.dist-info/WHEEL
ginodantic-0.1.0b2.dist-info/top_level.txt
ginodantic-0.1.0b2.dist-info/RECORD
