Metadata-Version: 2.1
Name: ginodantic
Version: 0.1.0b2
Summary: Ginodantic
Home-page: UNKNOWN
Author: Basalex (Alexander Baskakov)
Author-email: <alexanderbaskakov@mail.ru>
License: UNKNOWN
Project-URL: Source, https://github.com/Basalex/ginodantic
Keywords: python,pydantic,gino
Platform: UNKNOWN
Classifier: Development Status :: 4 - Beta
Classifier: Intended Audience :: Developers
Classifier: Programming Language :: Python :: 3
Classifier: Operating System :: Unix
Classifier: Operating System :: MacOS :: MacOS X
Classifier: Operating System :: Microsoft :: Windows
License-File: LICENSE.txt
Requires-Dist: pydantic
Requires-Dist: gino
